setup.py
projex_xqt.egg-info/PKG-INFO
projex_xqt.egg-info/SOURCES.txt
projex_xqt.egg-info/dependency_links.txt
projex_xqt.egg-info/top_level.txt
xqt/__init__.py
xqt/__revision__.py
xqt/pyi_hook.py
xqt/pyqt4_wrapper.py
xqt/pyside_wrapper.py