Metadata-Version: 1.0
Name: projex-xqt
Version: 1.1
Summary: UNKNOWN
Home-page: UNKNOWN
Author: Projex Software
Author-email: team@projexsoftware.com
License: LGPL
Platform: UNKNOWN
